large_image_source_openvisus/__init__.py
large_image_source_openvisus/girder_source.py
large_image_source_openvisus-1.0.9.dist-info/METADATA
large_image_source_openvisus-1.0.9.dist-info/WHEEL
large_image_source_openvisus-1.0.9.dist-info/entry_points.txt
large_image_source_openvisus-1.0.9.dist-info/top_level.txt
large_image_source_openvisus-1.0.9.dist-info/RECORD
